cms_fstyle/__init__.py
cms_fstyle/fitter.py
cms_fstyle/plotter.py
cms_fstyle/resources/correlation.png
cms_fstyle/resources/covariance.png
cms_fstyle/resources/covariance_proj.png
cms_fstyle/resources/fStyle.mplstyle
cms_fstyle/resources/sample.png
cms_fstyle/stats/__init__.py
cms_fstyle/stats/covariance.py
cms_fstyle/stats/rand_var.py
cms_fstyle_PG-2025.6.dist-info/METADATA
cms_fstyle_PG-2025.6.dist-info/WHEEL
cms_fstyle_PG-2025.6.dist-info/top_level.txt
cms_fstyle_PG-2025.6.dist-info/RECORD
