Metadata-Version: 2.1
Name: cms_fstyle_PG
Version: 2025.6
Summary: Package to get a proper matplolib style and ROOT-type histogram plotting and some stat/fitting methods
Home-page: https://gitlab.cern.ch/fcouderc/cms_fstyle
Author: Fabrice Couderc
Author-email: fabrice.couderc@cea.ch
Classifier: Programming Language :: Python
Classifier: License :: OSI Approved :: GNU General Public License v3 (GPLv3)
Classifier: Operating System :: OS Independent
Requires-Python: >=3.8
Requires-Dist: pandas
Requires-Dist: matplotlib
Requires-Dist: numpy
Provides-Extra: fitter
Requires-Dist: scikit-learn; extra == "fitter"
